django_dynamic_workflows-1.6.0.dist-info/licenses/LICENSE
django_workflow_engine/__init__.py
django_workflow_engine/action_executor.py
django_workflow_engine/action_handlers.py
django_workflow_engine/action_management.py
django_workflow_engine/action_registry.py
django_workflow_engine/admin.py
django_workflow_engine/apps.py
django_workflow_engine/choices.py
django_workflow_engine/cleanup.py
django_workflow_engine/constants.py
django_workflow_engine/default_actions.py
django_workflow_engine/enhanced_logging.py
django_workflow_engine/example_actions.py
django_workflow_engine/handlers.py
django_workflow_engine/logging_utils.py
django_workflow_engine/models.py
django_workflow_engine/notifications.py
django_workflow_engine/recipient_resolver.py
django_workflow_engine/serializers.py
django_workflow_engine/services.py
django_workflow_engine/settings.py
django_workflow_engine/signals.py
django_workflow_engine/strategy_handlers.py
django_workflow_engine/translation_utils.py
django_workflow_engine/urls.py
django_workflow_engine/utils.py
django_workflow_engine/views.py
django_workflow_engine/locale/ar/LC_MESSAGES/django.mo
django_workflow_engine/locale/ar/LC_MESSAGES/django.po
django_workflow_engine/locale/en/LC_MESSAGES/django.mo
django_workflow_engine/locale/en/LC_MESSAGES/django.po
django_workflow_engine/management/__init__.py
django_workflow_engine/management/commands/__init__.py
django_workflow_engine/management/commands/cleanup_workflows.py
django_workflow_engine/management/commands/compilemessages.py
django_workflow_engine/management/commands/setup_workflows.py
django_workflow_engine/migrations/0001_initial.py
django_workflow_engine/migrations/0002_alter_workflow_options_and_more.py
django_workflow_engine/migrations/0003_add_is_hidden_to_workflow.py
django_workflow_engine/migrations/0004_add_status_values_to_workflowconfiguration.py
django_workflow_engine/migrations/0005_add_workflow_strategy_system.py
django_workflow_engine/migrations/0006_fix_workflow_strategy_values.py
django_dynamic_workflows-1.6.0.dist-info/METADATA
django_dynamic_workflows-1.6.0.dist-info/WHEEL
django_dynamic_workflows-1.6.0.dist-info/top_level.txt
django_dynamic_workflows-1.6.0.dist-info/RECORD
