Metadata-Version: 2.4
Name: django-dynamic-workflows
Version: 1.6.0
Summary: A powerful, configurable Django package for implementing dynamic multi-step workflow processes with database-stored actions
Author-email: Mohamed Ibrahim <info@codxi.com>
License-Expression: MIT
Project-URL: Homepage, https://github.com/Codxi-Co/django-dynamic-workflows
Project-URL: Repository, https://github.com/Codxi-Co/django-dynamic-workflows.git
Project-URL: Documentation, https://github.com/Codxi-Co/django-dynamic-workflows#readme
Project-URL: Bug Tracker, https://github.com/Codxi-Co/django-dynamic-workflows/issues
Classifier: Development Status :: 5 - Production/Stable
Classifier: Environment :: Web Environment
Classifier: Framework :: Django
Classifier: Framework :: Django :: 5.2
Classifier: Framework :: Django :: 6.0
Classifier: Intended Audience :: Developers
Classifier: Operating System :: OS Independent
Classifier: Programming Language :: Python
Classifier: Programming Language :: Python :: 3.12
Classifier: Programming Language :: Python :: 3.13
Classifier: Topic :: Internet :: WWW/HTTP
Classifier: Topic :: Internet :: WWW/HTTP :: Dynamic Content
Classifier: Topic :: Software Development :: Libraries :: Python Modules
Requires-Python: >=3.10
License-File: LICENSE
Requires-Dist: Django>=5.2
Requires-Dist: django-approval-workflow>=0.9.0
Provides-Extra: api
Requires-Dist: djangorestframework; extra == "api"
Provides-Extra: dev
Requires-Dist: pytest; extra == "dev"
Requires-Dist: pytest-django; extra == "dev"
Requires-Dist: factory-boy; extra == "dev"
Requires-Dist: coverage; extra == "dev"
Requires-Dist: black; extra == "dev"
Requires-Dist: isort; extra == "dev"
Requires-Dist: flake8; extra == "dev"
Dynamic: license-file
